apatite/__init__.py
apatite/__main__.py
apatite/_version.py
apatite/cli.py
apatite/dal.py
apatite/formatting.py
apatite/utils.py
apatite/metrics/__init__.py
apatite/metrics/arch.py
apatite/metrics/gh.py
apatite/metrics/license.py
apatite/metrics/sloc.py
apatite/metrics/topic.py
apatite/metrics/vcs.py
apatite-20.0.1.dist-info/METADATA
apatite-20.0.1.dist-info/WHEEL
apatite-20.0.1.dist-info/entry_points.txt
apatite-20.0.1.dist-info/top_level.txt
apatite-20.0.1.dist-info/RECORD
