Metadata-Version: 2.1
Name: apatite
Version: 20.0.1
Summary: CLI for awesomer Awesome™ list management and analysis. Originally designed for managing https://github.com/mahmoud/awesome-python-applications
Home-page: https://github.com/mahmoud/apatite
Author: Mahmoud Hashemi
Author-email: mahmoud@hatnote.com
License: GPLv3
Platform: any
Requires-Dist: ashes
Requires-Dist: attrs
Requires-Dist: boltons
Requires-Dist: face
Requires-Dist: ruamel.yaml
Requires-Dist: glom
Requires-Dist: hyperlink
Requires-Dist: schema
Requires-Dist: tqdm
